citegeist/__init__.py
citegeist/generator.py
citegeist/utils/__init__.py
citegeist/utils/citations.py
citegeist/utils/filtering.py
citegeist/utils/helpers.py
citegeist/utils/prompts.py
citegeist/utils/llm_clients/__init__.py
citegeist/utils/llm_clients/anthropic_client.py
citegeist/utils/llm_clients/azure_client.py
citegeist/utils/llm_clients/base_client.py
citegeist/utils/llm_clients/gemini_client.py
citegeist/utils/llm_clients/mistral_client.py
citegeist/utils/llm_clients/openai_client.py
citegeist_arxiv-0.0.1.dist-info/METADATA
citegeist_arxiv-0.0.1.dist-info/WHEEL
citegeist_arxiv-0.0.1.dist-info/top_level.txt
citegeist_arxiv-0.0.1.dist-info/RECORD
