Metadata-Version: 2.4
Name: citegeist-arxiv
Version: 0.0.1
Summary: Generates a related work analysis including all used citations.
Author-email: Carl-Leander Henneking <ch2273@cornell.edu>, Claas Beger <cbb89@cornell.edu>
Project-URL: Repository, https://github.com/chenneking/citegeist
Requires-Python: >=3.12
Requires-Dist: bertopic<0.17.0,>=0.16.4
Requires-Dist: sentence-transformers<4.0.0,>=3.3.1
Requires-Dist: pymilvus<3.0.0,>=2.5.0
Requires-Dist: python-dotenv>=1.0.1
Requires-Dist: arxiv>=2.1.3
Requires-Dist: requests>=2.32.3
Requires-Dist: PyMuPDF>=1.24.14
Requires-Dist: scikit-learn>=1.5.2
Requires-Dist: python-dotenv>=1.0.1
Provides-Extra: webapp
Requires-Dist: fastapi<0.116.0,>=0.115.5; extra == "webapp"
Requires-Dist: uvicorn<0.33.0,>=0.32.1; extra == "webapp"
Requires-Dist: python-multipart>=0.0.18; extra == "webapp"
Requires-Dist: slowapi==0.1.9; extra == "webapp"
Provides-Extra: dev
Requires-Dist: black<26.0.0,>=25.1.0; extra == "dev"
Requires-Dist: flake8<8.0.0,>=7.1.2; extra == "dev"
Requires-Dist: isort<7.0.0,>=6.0.1; extra == "dev"
Requires-Dist: pre-commit<5.0.0,>=4.2.0; extra == "dev"
Provides-Extra: milvus-setup
Requires-Dist: pymilvus[bulk_writer]>=2.5.0; extra == "milvus-setup"
Requires-Dist: jsonlines>=4.0.0; extra == "milvus-setup"
Requires-Dist: torch>=2.5.1; extra == "milvus-setup"
Requires-Dist: numpy>=2.0.2; extra == "milvus-setup"
